enviroplus/__init__.py
enviroplus/gas.py
enviroplus/noise.py
enviroplus-0.0.6.dist-info/LICENSE.txt
enviroplus-0.0.6.dist-info/METADATA
enviroplus-0.0.6.dist-info/WHEEL
enviroplus-0.0.6.dist-info/top_level.txt
enviroplus-0.0.6.dist-info/RECORD
