Metadata-Version: 2.1
Name: enviroplus
Version: 0.0.6
Summary: Enviro pHAT Plus environmental monitoring add-on for Raspberry Pi
Home-page: https://www.pimoroni.com
Author: Philip Howard
Author-email: phil@pimoroni.com
License: MIT
Project-URL: GitHub, https://www.github.com/pimoroni/enviroplus-python
Keywords: Raspberry Pi
Platform: UNKNOWN
Classifier: Development Status :: 4 - Beta
Classifier: Operating System :: POSIX :: Linux
Classifier: License :: OSI Approved :: MIT License
Classifier: Intended Audience :: Developers
Classifier: Programming Language :: Python :: 3
Classifier: Topic :: Software Development
Classifier: Topic :: Software Development :: Libraries
Classifier: Topic :: System :: Hardware
Requires-Python: >=3.6
Requires-Dist: ads1015 (>=0.0.7)
Requires-Dist: astral
Requires-Dist: font-roboto
Requires-Dist: fonts
Requires-Dist: ltr559
Requires-Dist: paho-mqtt
Requires-Dist: pimoroni-bme280
Requires-Dist: pms5003
Requires-Dist: pytz
Requires-Dist: sounddevice
Requires-Dist: st7735
